{
	"name": "SQL script 1",
	"properties": {
		"content": {
			"query": "-- This is auto-generated code\nSELECT\n    TOP 100 *\nFROM\n    OPENROWSET(\n        BULK 'https://synapsetest2000.dfs.core.windows.net/synapsetest2000/Business-employment-data-september-2022-quarter-csv.csv',\n        FORMAT = 'CSV',\n        PARSER_VERSION = '2.0'\n    ) AS [result]\n",
			"metadata": {
				"language": "sql"
			},
			"currentConnection": {
				"databaseName": "master",
				"poolName": "Built-in"
			},
			"resultLimit": 5000
		},
		"type": "SqlQuery"
	}
}